pyprika/__init__.py
pyprika/const.py
pyprika/data/__init__.py
pyprika/data/local/__init__.py
pyprika/data/local/domain_data_store.py
pyprika/data/remote/__init__.py
pyprika/data/remote/paprika_client.py
pyprika/domain/__init__.py
pyprika/domain/specifications.py
pyprika/domain/work_units/__init__.py
pyprika/domain/work_units/backgroud_refresh_data.py
pyprika/domain/work_units/create_filter_specification.py
pyprika/domain/work_units/fetch_data.py
pyprika/domain/work_units/filter_recipes.py
pyprika/domain/work_units/link_models.py
pyprika/domain/work_units/store_models.py
pyprika/domain/work_units/transform_models.py
pyprika/framework/__init__.py
pyprika/framework/specifications.py
pyprika/framework/work_unit_base.py
pyprika/framework/containers/__init__.py
pyprika/framework/containers/data_container.py
pyprika/framework/containers/model_container.py
pyprika/framework/containers/work_unit_container.py
pyprika/framework/models/__init__.py
pyprika/framework/models/base_model.py
pyprika/framework/models/bookmark.py
pyprika/framework/models/category.py
pyprika/framework/models/grocery_item.py
pyprika/framework/models/meal.py
pyprika/framework/models/menu.py
pyprika/framework/models/menu_item.py
pyprika/framework/models/pantry_item.py
pyprika/framework/models/recipe.py
pyprika/framework/models/recipe_item.py
pyprika/framework/models/status.py
pyprika_client-0.2.1.dist-info/LICENSE
pyprika_client-0.2.1.dist-info/METADATA
pyprika_client-0.2.1.dist-info/WHEEL
pyprika_client-0.2.1.dist-info/top_level.txt
pyprika_client-0.2.1.dist-info/RECORD
