Metadata-Version: 2.1
Name: pyprika-client
Version: 0.2.1
Summary: AsyncIO Library for Communicating with Paprika backend servers.
Home-page: https://github.com/constructorfleet/pyprika
Author: Teagan Glenn
Author-email: that@teagantotally.rocks
License: MIT
Keywords: Paprika,Cooking,Recipes
Classifier: Development Status :: 4 - Beta
Classifier: Intended Audience :: Developers
Classifier: Natural Language :: English
Classifier: Programming Language :: Python :: 3
Classifier: Programming Language :: Python :: 3.5
Classifier: Programming Language :: Python :: 3.6
Classifier: Programming Language :: Python :: 3.7
Classifier: Programming Language :: Python :: 3.8
License-File: LICENSE
Requires-Dist: aiohttp (==3.8.1)
Requires-Dist: asyncio (==3.4.3)
Requires-Dist: attrs (==19.3.0)
Requires-Dist: chardet (==3.0.4)
Requires-Dist: idna (==2.8)
Requires-Dist: multidict
Requires-Dist: yarl (==1.4.2)
